setup.py
gauss_dsnd/Binomialdistribution.py
gauss_dsnd/Gaussiandistribution.py
gauss_dsnd/Generaldistribution.py
gauss_dsnd/__init__.py
gauss_dsnd.egg-info/PKG-INFO
gauss_dsnd.egg-info/SOURCES.txt
gauss_dsnd.egg-info/dependency_links.txt
gauss_dsnd.egg-info/not-zip-safe
gauss_dsnd.egg-info/top_level.txt