Metadata-Version: 1.0
Name: gauss-dsnd
Version: 1.0
Summary: Gaussian and Binomial distributions
Home-page: UNKNOWN
Author: Vikram Shinde
Author-email: shindevikram1210@gmail.com
License: UNKNOWN
Platform: UNKNOWN
